vspk/__init__.py
vspk/utils.py
vspk/cli/__init__.py
vspk/cli/cli.py
vspk/cli/commands.py
vspk/cli/printer.py
vspk/cli/utils.py
vspk/v5_0/__init__.py
vspk/v5_0/nuaddressmap.py
vspk/v5_0/nuaddressrange.py
vspk/v5_0/nuaggregatemetadata.py
vspk/v5_0/nualarm.py
vspk/v5_0/nuallalarm.py
vspk/v5_0/nuallgateway.py
vspk/v5_0/nuallredundancygroup.py
vspk/v5_0/nuapplication.py
vspk/v5_0/nuapplicationbinding.py
vspk/v5_0/nuapplicationperformancemanagement.py
vspk/v5_0/nuapplicationperformancemanagementbinding.py
vspk/v5_0/nuautodiscovercluster.py
vspk/v5_0/nuautodiscovereddatacenter.py
vspk/v5_0/nuautodiscoveredgateway.py
vspk/v5_0/nuautodiscoverhypervisorfromcluster.py
vspk/v5_0/nuavatar.py
vspk/v5_0/nubfdsession.py
vspk/v5_0/nubgpneighbor.py
vspk/v5_0/nubgppeer.py
vspk/v5_0/nubgpprofile.py
vspk/v5_0/nubootstrap.py
vspk/v5_0/nubootstrapactivation.py
vspk/v5_0/nubrconnection.py
vspk/v5_0/nubridgeinterface.py
vspk/v5_0/nubulkstatistics.py
vspk/v5_0/nucaptiveportalprofile.py
vspk/v5_0/nucertificate.py
vspk/v5_0/nucloudmgmtsystem.py
vspk/v5_0/nucommand.py
vspk/v5_0/nuconnectionendpoint.py
vspk/v5_0/nucontainer.py
vspk/v5_0/nucontainerinterface.py
vspk/v5_0/nucontainerresync.py
vspk/v5_0/nucosremarkingpolicy.py
vspk/v5_0/nucosremarkingpolicytable.py
vspk/v5_0/nucsnatpool.py
vspk/v5_0/nuctranslationmap.py
vspk/v5_0/nucustomproperty.py
vspk/v5_0/nudefaultgateway.py
vspk/v5_0/nudemarcationservice.py
vspk/v5_0/nudeploymentfailure.py
vspk/v5_0/nudestinationurl.py
vspk/v5_0/nudhcpoption.py
vspk/v5_0/nudiskstat.py
vspk/v5_0/nudomain.py
vspk/v5_0/nudomainfipacltemplate.py
vspk/v5_0/nudomainfipacltemplateentry.py
vspk/v5_0/nudomaintemplate.py
vspk/v5_0/nudownloadprogress.py
vspk/v5_0/nudscpforwardingclassmapping.py
vspk/v5_0/nudscpforwardingclasstable.py
vspk/v5_0/nudscpremarkingpolicy.py
vspk/v5_0/nudscpremarkingpolicytable.py
vspk/v5_0/nuducgroup.py
vspk/v5_0/nuducgroupbinding.py
vspk/v5_0/nuegressaclentrytemplate.py
vspk/v5_0/nuegressacltemplate.py
vspk-20.10.15.dist-info/LICENSE
vspk-20.10.15.dist-info/METADATA
vspk-20.10.15.dist-info/WHEEL
vspk-20.10.15.dist-info/entry_points.txt
vspk-20.10.15.dist-info/top_level.txt
vspk-20.10.15.dist-info/RECORD
