Metadata-Version: 2.1
Name: vspk
Version: 20.10.15
Summary: SDK for the VSD API
Home-page: http://nuagenetworks.net/
Author: nuage networks
Author-email: opensource@nuagenetworks.net
License: BSD-3
License-File: LICENSE
Requires-Dist: bambou <4.0,>=3.1
Requires-Dist: tabulate
Requires-Dist: colorama
